streaminghub_proxy_lsl/__init__.py
streaminghub_proxy_lsl/lsl.py
streaminghub_proxy_lsl/proxy.py
streaminghub_proxy_lsl/test.py
streaminghub_proxy_lsl/util.py
streaminghub_proxy_lsl-0.0.1.dist-info/METADATA
streaminghub_proxy_lsl-0.0.1.dist-info/WHEEL
streaminghub_proxy_lsl-0.0.1.dist-info/entry_points.txt
streaminghub_proxy_lsl-0.0.1.dist-info/top_level.txt
streaminghub_proxy_lsl-0.0.1.dist-info/RECORD
